contenders/__init__.py
contenders/components.py
contenders/scores.csv
contenders-0.1.1.dist-info/entry_points.txt
contenders-0.1.1.dist-info/WHEEL
contenders-0.1.1.dist-info/METADATA
contenders-0.1.1.dist-info/RECORD
