Metadata-Version: 2.1
Name: contenders
Version: 0.1.1
Summary: A self-hosted programming challenge framework.
Home-page: UNKNOWN
License: UNKNOWN
Author: Jeremiah Boby
Author-email: mail@jeremiahboby.me
Requires-Python: >=3.7,<4.0
Classifier: Programming Language :: Python :: 3
Classifier: Programming Language :: Python :: 3.7
Requires-Dist: dash (>=0.40.0,<0.41.0)
Requires-Dist: dash-bootstrap-components (>=0.3.5,<0.4.0)
Requires-Dist: dash-table (>=3.6,<4.0)
Requires-Dist: docopt (>=0.6.2,<0.7.0)
Requires-Dist: pandas (>=0.24.2,<0.25.0)
